{"rowCount":6,"colCount":6,"type":0,"letters":"AILPR","words":[{"word":"APRIL","vertical":false,"rowIndex":1,"colIndex":0,"coinIndices":[],"awardCoins":false},{"word":"PAR","vertical":true,"rowIndex":3,"colIndex":2,"coinIndices":[],"awardCoins":false},{"word":"PAIR","vertical":true,"rowIndex":0,"colIndex":0,"coinIndices":[],"awardCoins":false},{"word":"API","vertical":true,"rowIndex":3,"colIndex":4,"coinIndices":[],"awardCoins":false},{"word":"RAIL","vertical":false,"rowIndex":5,"colIndex":2,"coinIndices":[],"awardCoins":false},{"word":"RAP","vertical":false,"rowIndex":3,"colIndex":0,"coinIndices":[],"awardCoins":false},{"word":"LIP","vertical":true,"rowIndex":0,"colIndex":3,"coinIndices":[],"awardCoins":false}],"id":"44f38a9fd5708ca3f7a045c5f240378b"}