{"rowCount":11,"colCount":11,"type":0,"letters":"DEEEQRSTU","words":[{"word":"REQUESTED","vertical":false,"rowIndex":6,"colIndex":2,"coinIndices":[],"awardCoins":false},{"word":"QUEST","vertical":true,"rowIndex":6,"colIndex":4,"coinIndices":[],"awardCoins":false},{"word":"USE","vertical":false,"rowIndex":7,"colIndex":0,"coinIndices":[],"awardCoins":false},{"word":"REQUEST","vertical":true,"rowIndex":0,"colIndex":8,"coinIndices":[],"awardCoins":false},{"word":"USED","vertical":true,"rowIndex":7,"colIndex":0,"coinIndices":[],"awardCoins":false},{"word":"SEE","vertical":true,"rowIndex":4,"colIndex":6,"coinIndices":[],"awardCoins":false},{"word":"USER","vertical":false,"rowIndex":9,"colIndex":3,"coinIndices":[],"awardCoins":false},{"word":"SET","vertical":true,"rowIndex":6,"colIndex":7,"coinIndices":[],"awardCoins":false},{"word":"SURE","vertical":true,"rowIndex":3,"colIndex":3,"coinIndices":[],"awardCoins":false},{"word":"RED","vertical":true,"rowIndex":6,"colIndex":2,"coinIndices":[],"awardCoins":false},{"word":"TRUE","vertical":false,"rowIndex":4,"colIndex":1,"coinIndices":[],"awardCoins":false},{"word":"DUE","vertical":true,"rowIndex":6,"colIndex":10,"coinIndices":[],"awardCoins":false},{"word":"TREE","vertical":false,"rowIndex":0,"colIndex":7,"coinIndices":[],"awardCoins":false}],"id":"857b605aeeefb2c06a719424818701ef"}