{"rowCount":6,"colCount":9,"type":0,"letters":"EHNOPS","words":[{"word":"PHONES","vertical":false,"rowIndex":3,"colIndex":1,"coinIndices":[],"awardCoins":false},{"word":"OPEN","vertical":true,"rowIndex":0,"colIndex":4,"coinIndices":[],"awardCoins":false},{"word":"ONE","vertical":false,"rowIndex":4,"colIndex":6,"coinIndices":[],"awardCoins":false},{"word":"PHONE","vertical":true,"rowIndex":0,"colIndex":8,"coinIndices":[],"awardCoins":false},{"word":"SHOP","vertical":true,"rowIndex":0,"colIndex":1,"coinIndices":[],"awardCoins":false},{"word":"SHE","vertical":false,"rowIndex":1,"colIndex":0,"coinIndices":[],"awardCoins":false},{"word":"HOPES","vertical":false,"rowIndex":5,"colIndex":0,"coinIndices":[],"awardCoins":false},{"word":"SON","vertical":true,"rowIndex":3,"colIndex":6,"coinIndices":[],"awardCoins":false},{"word":"HOPE","vertical":false,"rowIndex":0,"colIndex":3,"coinIndices":[],"awardCoins":false},{"word":"HOP","vertical":true,"rowIndex":3,"colIndex":2,"coinIndices":[],"awardCoins":false}],"id":"71db671d89461581db13f83485c1a647"}