{"rowCount":9,"colCount":10,"type":0,"letters":"EENPRST","words":[{"word":"PRESENT","vertical":true,"rowIndex":2,"colIndex":4,"coinIndices":[],"awardCoins":false},{"word":"ENTER","vertical":false,"rowIndex":3,"colIndex":0,"coinIndices":[],"awardCoins":false},{"word":"TEEN","vertical":false,"rowIndex":6,"colIndex":2,"coinIndices":[],"awardCoins":false},{"word":"SEE","vertical":true,"rowIndex":0,"colIndex":5,"coinIndices":[],"awardCoins":false},{"word":"ENTERS","vertical":false,"rowIndex":4,"colIndex":4,"coinIndices":[],"awardCoins":false},{"word":"SET","vertical":true,"rowIndex":4,"colIndex":9,"coinIndices":[],"awardCoins":false},{"word":"PETER","vertical":false,"rowIndex":2,"colIndex":4,"coinIndices":[],"awardCoins":false},{"word":"STEP","vertical":false,"rowIndex":0,"colIndex":5,"coinIndices":[],"awardCoins":false},{"word":"NET","vertical":false,"rowIndex":1,"colIndex":0,"coinIndices":[],"awardCoins":false},{"word":"SPENT","vertical":false,"rowIndex":8,"colIndex":0,"coinIndices":[],"awardCoins":false},{"word":"SEEN","vertical":true,"rowIndex":0,"colIndex":1,"coinIndices":[],"awardCoins":false}],"id":"81fcd73f11b8ff3c728d17f22d68f921"}