{"rowCount":8,"colCount":8,"type":0,"letters":"BDEINTU","words":[{"word":"DEBUT","vertical":false,"rowIndex":0,"colIndex":0,"coinIndices":[0,1,2,3,4],"awardCoins":true},{"word":"UNITED","vertical":false,"rowIndex":5,"colIndex":2,"coinIndices":[],"awardCoins":false},{"word":"EDIT","vertical":true,"rowIndex":4,"colIndex":7,"coinIndices":[],"awardCoins":false},{"word":"BUT","vertical":false,"rowIndex":4,"colIndex":0,"coinIndices":[],"awardCoins":false},{"word":"UNIT","vertical":true,"rowIndex":2,"colIndex":5,"coinIndices":[],"awardCoins":false},{"word":"END","vertical":false,"rowIndex":3,"colIndex":4,"coinIndices":[],"awardCoins":false},{"word":"DEBT","vertical":true,"rowIndex":2,"colIndex":0,"coinIndices":[],"awardCoins":false},{"word":"NET","vertical":false,"rowIndex":7,"colIndex":5,"coinIndices":[],"awardCoins":false},{"word":"DIET","vertical":false,"rowIndex":2,"colIndex":0,"coinIndices":[],"awardCoins":false},{"word":"DUE","vertical":false,"rowIndex":7,"colIndex":0,"coinIndices":[],"awardCoins":false},{"word":"TUBE","vertical":true,"rowIndex":4,"colIndex":2,"coinIndices":[],"awardCoins":false}],"id":"dbe7f490dc9471d693f14279a7bcc8cc"}