{"rowCount":9,"colCount":9,"type":0,"letters":"EFFORST","words":[{"word":"OFFSET","vertical":false,"rowIndex":0,"colIndex":0,"coinIndices":[0,1,2,3,4,5],"awardCoins":true},{"word":"SOFT","vertical":false,"rowIndex":2,"colIndex":2,"coinIndices":[],"awardCoins":false},{"word":"EFFORTS","vertical":true,"rowIndex":2,"colIndex":0,"coinIndices":[],"awardCoins":false},{"word":"FOR","vertical":false,"rowIndex":4,"colIndex":0,"coinIndices":[],"awardCoins":false},{"word":"OFFERS","vertical":true,"rowIndex":3,"colIndex":6,"coinIndices":[],"awardCoins":false},{"word":"OFFER","vertical":false,"rowIndex":4,"colIndex":4,"coinIndices":[],"awardCoins":false},{"word":"SORT","vertical":true,"rowIndex":2,"colIndex":2,"coinIndices":[],"awardCoins":false},{"word":"SET","vertical":false,"rowIndex":8,"colIndex":0,"coinIndices":[],"awardCoins":false},{"word":"FOREST","vertical":true,"rowIndex":2,"colIndex":8,"coinIndices":[],"awardCoins":false},{"word":"FROST","vertical":true,"rowIndex":2,"colIndex":4,"coinIndices":[],"awardCoins":false},{"word":"REST","vertical":false,"rowIndex":8,"colIndex":4,"coinIndices":[],"awardCoins":false}],"id":"b076d311016821d5f943d60dbe5308d9"}